sphinx_all_contributors/__init__.py
sphinx_all_contributors/directive.py
sphinx_all_contributors-0.2.0.dist-info/LICENSE
sphinx_all_contributors-0.2.0.dist-info/METADATA
sphinx_all_contributors-0.2.0.dist-info/WHEEL
sphinx_all_contributors-0.2.0.dist-info/top_level.txt
sphinx_all_contributors-0.2.0.dist-info/RECORD
