Metadata-Version: 2.1
Name: sphinx-all-contributors
Version: 0.2.0
Requires-Python: >=3.12
License-File: LICENSE
Provides-Extra: all
Requires-Dist: sphinx-all-contributors[docs]; extra == "all"
Provides-Extra: docs
Requires-Dist: sphinx-book-theme==1.1.3; extra == "docs"
